zeither/__init__.py
zeither/either.py
zeither-0.2.0.dist-info/WHEEL
zeither-0.2.0.dist-info/METADATA
zeither-0.2.0.dist-info/RECORD
