Metadata-Version: 2.1
Name: zeither
Version: 0.2.0
Summary: A either python package (study purpose)
Author: tba
Requires-Python: >=3.9,<4.0
Classifier: Programming Language :: Python :: 3
Classifier: Programming Language :: Python :: 3.9
